poodle/__init__.py
poodle/auth.py
poodle/constants.py
poodle/corews.py
poodle/credentials.py
poodle/poodle.py
poodle/py.typed
poodle/typedefs/__init__.py
poodle/typedefs/assign.py
poodle/typedefs/course.py
poodle/typedefs/courses.py
poodle/typedefs/exception.py
poodle/typedefs/groups.py
poodle/typedefs/jsonable.py
poodle/typedefs/methods.py
poodle/typedefs/site.py
poodle/typedefs/tag.py
poodle/typedefs/ws.py
poodle/util/__init__.py
poodle/util/cache.py
poodle/util/loggable.py
poodle/util/parse_form.py
poodle/util/tokens.py
bchmnn.poodle-0.2.6.dist-info/LICENSE
bchmnn.poodle-0.2.6.dist-info/METADATA
bchmnn.poodle-0.2.6.dist-info/WHEEL
bchmnn.poodle-0.2.6.dist-info/top_level.txt
bchmnn.poodle-0.2.6.dist-info/RECORD
