Metadata-Version: 2.1
Name: bchmnn.poodle
Version: 0.2.6
Summary: Python Moodle SDK
Author-email: Jacob Bachmann <jacob.bachmann@posteo.de>
License: GNU GENERAL PUBLIC LICENSE
Project-URL: Homepage, https://github.com/bchmnn/poodle
Keywords: moodle,sdk,api
Classifier: Development Status :: 2 - Pre-Alpha
Classifier: License :: OSI Approved :: GNU General Public License v3 (GPLv3)
Classifier: License :: OSI Approved :: MIT License
Classifier: Programming Language :: Python
Classifier: Programming Language :: Python :: 3
Requires-Python: >=3.11
License-File: LICENSE
Requires-Dist: aiohttp (>=3.8.0)
Provides-Extra: dev
Requires-Dist: black ; extra == 'dev'
Requires-Dist: pip-tools ; extra == 'dev'
Requires-Dist: bumpver ; extra == 'dev'
Requires-Dist: build ; extra == 'dev'
Requires-Dist: twine ; extra == 'dev'
Requires-Dist: git-changelog ; extra == 'dev'
Requires-Dist: mypy ; extra == 'dev'
Requires-Dist: pylint ; extra == 'dev'
Requires-Dist: isort ; extra == 'dev'
